{"Accessibility": ["TaxiRankOutsideStation", "SpecificEntranceRequired", "AddtionalInformation", "LimitedCapacityLift", "ToiletNote", "SpecificEntranceInstructions", "Toilet", "AccessViaLift", "BlueBadgeCarParkSpaces"], "Address": ["Address", "PhoneNo"], "Direction": ["Towards", "CompassPoint"], "Facility": ["Boarding Ramp", "Lifts", "Cash Machines", "Waiting Room", "Boarding Ramps", "Escalators", "Bridge", "Car park", "ASDA Click and Collect", "Ticket Halls", "Help Points", "WiFi", "Left Luggage", "Photo Booths", "Amazon Lockers", "Other Facilities", "Euro Cash Machines", "Payphones", "Gates", "Toilets"], "Geo": ["Zone"], "NearestPlaces": ["SourceSystemPlaceId"], "Opening Time": ["SunFrom", "MonFriTo", "SatTo", "MonFriFrom", "SunTo", "SatFrom"], "ServiceInfo": ["Night"], "StationOwnedByTfl": ["OwnedByTfl"], "VisitorCentre": ["Location"]}